{
  "m68773:para:fs-idm2181616": {
    "terms": [
      {
        "id": "term-00001"
      }
    ]
  },
  "m68773:para:fs-idp68860560": {
    "terms": [
      {
        "id": "term-00002"
      },
      {
        "id": "term-00003"
      }
    ]
  },
  "m68773:para:fs-idm2044016": {
    "terms": [
      {
        "id": "term-00004"
      }
    ]
  },
  "m68773:para:fs-idp589840": {
    "terms": [
      {
        "id": "term-00005"
      },
      {
        "id": "term-00006"
      }
    ]
  },
  "m68773:para:fs-idp78313376": {
    "terms": [
      {
        "id": "term-00007"
      }
    ]
  },
  "m68773:para:fs-idm23808480": {
    "terms": [
      {
        "id": "term-00008"
      }
    ]
  },
  "m68773:para:fs-idp30613264": {
    "terms": [
      {
        "id": "term-00009"
      }
    ]
  },
  "m68773:para:fs-idp4268832": {
    "terms": [
      {
        "id": "term-00010"
      }
    ]
  },
  "m68773:para:fs-idp178963488": {
    "terms": [
      {
        "id": "term-00011"
      }
    ]
  },
  "m68773:para:fs-idp1330336": {
    "terms": [
      {
        "id": "term-00012"
      },
      {
        "id": "term-00013"
      },
      {
        "id": "term-00014"
      }
    ]
  },
  "m68773:para:fs-idm41755200": {
    "terms": [
      {
        "id": "term-00015"
      }
    ]
  },
  "m68773:para:fs-idp81646992": {
    "terms": [
      {
        "id": "term-00016"
      },
      {
        "id": "term-00017"
      }
    ]
  },
  "m68773:para:fs-idp173470256": {
    "terms": [
      {
        "id": "term-00018"
      },
      {
        "class": "no-emphasis",
        "id": "term-00019"
      }
    ]
  },
  "m68773:para:fs-idp1774112": {
    "terms": [
      {
        "class": "no-emphasis",
        "id": "term-00020"
      },
      {
        "class": "no-emphasis",
        "id": "term-00021"
      },
      {
        "class": "no-emphasis",
        "id": "term-00022"
      },
      {
        "class": "no-emphasis",
        "id": "term-00023"
      }
    ]
  }
}