{
  "module": "m68808",
  "section": "",
  "title": "Buffers",
  "equations": {
    "EQ:1": "{{{\\text{CH}}}_{3}{{\\text{CO}}}_{2}\\text{H}(aq)+{\\text{H}}_{2}\\text{O}(l)\\,⇌\\,{\\text{H}}_{3}{\\text{O}}^{\\text{+}}(aq)+{{\\text{CH}}}_{3}{{\\text{CO}}}_{2}^{\\text{−}}(aq)}",
    "EQ:2": "{x=1.8\\,\\times \\,{{10}}^{{−5}}M}",
    "EQ:3": "{{[{{\\text{H}}_{3}{\\text{O}}^{\\text{+}}}]}\\,=0+x=1.8\\,\\times \\,{{10}}^{{−5}}\\,M}",
    "EQ:4": "{\\text{pH}=\\text{−log}{[{{\\text{H}}_{3}{\\text{O}}^{\\text{+}}}]}\\,=\\,\\text{−log}{({1.8\\,\\times \\,{{10}}^{{−5}}})}}",
    "EQ:5": "{=4.74}",
    "EQ:6": "{0.0010\\,\\text{L}\\,\\times \\,{({\\,\\frac{{0.10\\,\\text{mol NaOH}}}{{1\\,\\text{L}}}})\\,}\\,=1.0\\,\\times \\,{{10}}^{{−4}}\\,\\text{mol NaOH}}",
    "EQ:7": "{0.100\\,\\text{L}\\,\\times \\,{({\\,\\frac{{0.100\\,\\text{mol}\\,{{\\text{CH}}}_{3}{{\\text{CO}}}_{2}\\text{H}}}{{1\\,\\text{L}}}})\\,}\\,=1.00\\,\\times \\,{{10}}^{{−2}}\\,\\text{mol}\\,{{\\text{CH}}}_{3}{{\\text{CO}}}_{2}\\text{H}}",
    "EQ:8": "{(1.0\\,\\times \\,{{10}}^{{−2}})\\,-\\,(0.01\\,\\times \\,{{10}}^{{−2}})\\,=0.99\\,\\times \\,{{10}}^{{−2}}\\,\\text{mol}\\,{{\\text{CH}}}_{3}{{\\text{CO}}}_{2}\\text{H}}",
    "EQ:9": "{(1.0\\,\\times \\,{{10}}^{{−2}})+(0.01\\,\\times \\,{{10}}^{{−2}})\\,=1.01\\,\\times \\,{{10}}^{{−2}}\\text{mol}\\,{{\\text{NaCH}}}_{3}{{\\text{CO}}}_{2}}",
    "EQ:10": "{{[{{{\\text{CH}}}_{3}{{\\text{CO}}}_{2}\\text{H}}]}\\,=\\,\\frac{{9.9\\,\\times \\,{{10}}^{{−3}}\\,\\text{mol}}}{{0.101\\,\\text{L}}}\\,=0.098\\,M}",
    "EQ:11": "{{[{{{\\text{NaCH}}}_{3}{{\\text{CO}}}_{2}}]}\\,=\\,\\frac{{1.01\\,\\times \\,{{10}}^{{−2}}\\,\\text{mol}}}{{0.101\\,\\text{L}}}\\,=0.100\\,M}",
    "EQ:12": "{ [{\\text{H}}_{3} {\\text{O}}^{+} ]={{ 10}}^{{ -4.74}} =1.8\\,\\times \\,{{ 10}}^{{ -5}} \\,M}",
    "EQ:13": "\\text{mol}\\,{\\text{H}}_{3} {\\text{O}}^{+} =(0.100\\,L)(1.8\\,\\times \\,{10}^{{ −5}} \\,M)=1.8\\,\\times \\,{10}^{{ −6}} \\,\\text{mol}\\,{\\text{H}}_{3} {\\text{O}}^{+}",
    "EQ:14": "\\text{mol}\\,{\\text{OH}}^{-} =(0.0010\\,L)(0.10\\,M)=1.0\\,\\times \\,{10}^{{ −4}} \\,\\text{mol}\\,{\\text{OH}}^{-}",
    "EQ:15": "{\\text{H}}_{3} {\\text{O}}^{+} (aq)+{\\text{OH}}^{-} (aq)\\,⇋2{\\text{H}}_{2} \\text{O}(l)",
    "EQ:16": "1.0\\,\\times \\,{10}^{{ −4}} \\,\\text{mol}\\,-1.8\\,\\times \\,{10}^{{ −6}} \\text{mol}=9.8\\,\\times \\,{10}^{{ −5}} \\,\\text{mol}\\,{\\text{OH}}^{-}",
    "EQ:17": "9.8\\,\\times \\,{10}^{{ −5}} \\,\\text{mol}\\,{\\text{OH}}^{-} \\text{/}0.101\\,L=9.7\\,\\times \\,{10}^{{ −4}} \\,M",
    "EQ:18": "\\text{pH}=14.00-\\text{pOH}=14.00--\\text{log}(9.7\\,\\times \\,{10}^{{ −4}} )=10.99",
    "EQ:19": "\\times",
    "EQ:20": "\\times",
    "EQ:21": "\\times",
    "EQ:22": "\\times",
    "EQ:23": "\\times",
    "EQ:24": "\\times",
    "EQ:25": "\\times",
    "EQ:26": "\\times",
    "EQ:27": "\\times",
    "EQ:28": "{\\text{pH}=\\text{−log}[{\\text{H}}_{3}{\\text{O}}^{\\text{+}}]=\\text{−log}{({\\,\\frac{{\\text{total moles}\\,{\\text{H}}_{3}{\\text{O}}^{\\text{+}}}}{{\\text{total volume}}}})\\,}\\,=\\text{−log}{({\\,\\frac{{1.0\\,\\times \\,{{10}}^{{−4}}\\,\\text{mol}+1.8\\,\\times \\,{{10}}^{{−6}}\\,\\text{mol}}}{{101\\,\\text{mL}{({\\,{1\\,\\text{L}}{1000\\,\\text{mL}}}})\\,}}})\\,}\\,=3.00}",
    "EQ:29": "{[{{\\text{CH}}}_{3}{{\\text{CO}}}_{2}^{\\text{−}}]\\,=0.10\\,M.}",
    "EQ:30": "{{{\\text{HCO}}}_{3}^{\\text{−}}.}",
    "EQ:31": "{{\\text{H}}_{3}{\\text{O}}^{\\text{+}}(aq)+{{\\text{HCO}}}_{3}^{\\text{−}}(aq)\\,\\longrightarrow \\,{\\text{H}}_{2}{{\\text{CO}}}_{3}(aq)+{\\text{H}}_{2}\\text{O}(l)}",
    "EQ:32": "{{{\\text{OH}}}^{\\text{−}}(aq)+{\\text{H}}_{2}{{\\text{CO}}}_{3}(aq)\\,\\longrightarrow \\,{{\\text{HCO}}}_{3}^{\\text{−}}(aq)+{\\text{H}}_{2}\\text{O}(l)}",
    "EQ:33": "{{K}_{\\text{a}}=\\,\\frac{{{[{{\\text{H}}_{3}{\\text{O}}^{\\text{+}}}]}{[{{\\text{A}}^{\\text{−}}}]}}}{{{\\text{[HA]}}}}}",
    "EQ:34": "{{[{{\\text{H}}_{3}{\\text{O}}^{\\text{+}}}]}={K}_{\\text{a}}\\,\\times \\,\\frac{{{\\text{[HA]}}}}{{{[{{\\text{A}}^{\\text{−}}}]}}}}",
    "EQ:35": "{\\text{−log}{[{{\\text{H}}_{3}{\\text{O}}^{\\text{+}}}]}\\,=\\,\\text{−log}{K}_{\\text{a}}\\text{− log}\\frac{{{[{\\text{HA}}]}}}{{{[{{\\text{A}}^{\\text{−}}}]}}}\\,,}",
    "EQ:36": "{\\text{pH}=\\text{p}{K}_{\\text{a}}+\\text{log}\\,\\frac{{{[{{\\text{A}}^{\\text{−}}}]}}}{{{[{\\text{HA}}]}}}}",
    "EQ:37": "{{{\\text{CO}}}_{2}(g)+2{\\text{H}}_{2}\\text{O}(l)\\,⇌\\,{\\text{H}}_{2}{{\\text{CO}}}_{3}(aq)\\,⇌\\,{{\\text{HCO}}}_{3}^{\\text{−}}(aq)+{\\text{H}}_{3}{\\text{O}}^{\\text{+}}(aq)}",
    "EQ:38": "{{{\\text{HCO}}}_{3}^{\\text{−}},}",
    "EQ:39": "{\\text{pH}=\\text{p}{K}_{\\text{a}}+\\text{log}\\,\\frac{{{[{\\text{base}}]}}}{{{[{\\text{acid}}]}}}\\,=6.4+\\text{log}\\,\\frac{{0.024}}{{0.0012}}\\,=7.7}",
    "EQ:40": "{{{\\text{HCO}}}_{3}^{\\text{−}}}",
    "EQ:41": "{{{\\text{HCO}}}_{3}^{\\text{−}}}",
    "EQ:42": "{\\text{pH}=\\text{p}{K}_{\\text{a}}+\\text{log}\\,\\frac{{{[{{\\text{A}}^{\\text{−}}}]}}}{{{[{\\text{HA}}]}}}}",
    "EQ:43": "{{\\text{H}}_{3}{\\text{O}}^{\\text{+}}(aq)+{\\text{H}}_{2}{{\\text{PO}}}_{4}^{\\text{−}}(aq)\\,\\longrightarrow \\,{\\text{H}}_{3}{{\\text{PO}}}_{4}(aq)+{\\text{H}}_{2}\\text{O}(l)}",
    "EQ:44": "{{{\\text{OH}}}^{\\text{−}}(aq)+{\\text{H}}_{3}{{\\text{PO}}}_{4}(aq)\\,\\longrightarrow \\,{\\text{H}}_{2}{{\\text{PO}}}_{4}^{\\text{−}}(aq)+{\\text{H}}_{2}\\text{O}(l)}",
    "EQ:45": "{{{\\text{CH}}}_{3}{{\\text{CO}}}_{2}\\text{H}(aq)+{\\text{H}}_{2}\\text{O}(l)\\,⇌\\,{\\text{H}}_{3}{\\text{O}}^{\\text{+}}(aq)+{{\\text{CH}}}_{3}{{\\text{CO}}}_{2}^{\\text{−}}(aq)\\,{K}_{\\text{a}}=1.8\\,\\times \\,{{10}}^{{−5}}}",
    "EQ:46": "\\times",
    "EQ:47": "{{{\\text{HNO}}}_{2}(aq)+{\\text{H}}_{2}\\text{O}(l)\\,⇌\\,{\\text{H}}_{3}{\\text{O}}^{\\text{+}}(aq)+{{\\text{NO}}}_{2}^{\\text{−}}(aq)\\,{K}_{\\text{a}}=4.5\\,\\times \\,{{10}}^{{−5}}}",
    "EQ:48": "{{{\\text{CH}}}_{3}{{\\text{NH}}}_{2}(aq)+{\\text{H}}_{2}\\text{O}(l)\\,⇌\\,{{\\text{CH}}}_{3}{{\\text{NH}}}_{3}^{\\text{+}}(aq)+{{\\text{OH}}}^{\\text{−}}(aq)\\,{K}_{\\text{b}}=4.4\\,\\times \\,{{10}}^{{−4}}}",
    "EQ:49": "\\times",
    "EQ:50": "{{{\\text{NH}}}_{3}(aq)+{\\text{H}}_{2}\\text{O}(l)\\,⇌\\,{{\\text{NH}}}_{4}^{\\text{+}}(aq)+{{\\text{OH}}}^{\\text{−}}(aq)\\,{K}_{\\text{b}}=1.8\\,\\times \\,{{10}}^{{−5}}}",
    "EQ:51": "{{{\\text{CH}}}_{3}{{\\text{CO}}}_{2}^{\\text{−}}}",
    "EQ:52": "{[{{\\text{CH}}}_{3}{{\\text{CO}}}_{2}^{\\text{−}}]}",
    "EQ:53": "{[{{\\text{CH}}}_{3}{{\\text{CO}}}_{2}^{\\text{−}}]}",
    "EQ:54": "{[{{\\text{CH}}}_{3}{{\\text{CO}}}_{2}^{\\text{−}}]}",
    "EQ:55": "{[{{\\text{CH}}}_{3}{{\\text{CO}}}_{2}^{\\text{−}}]}",
    "EQ:56": "{[{{\\text{CH}}}_{3}{{\\text{CO}}}_{2}^{\\text{−}}]}",
    "EQ:57": "{[{{\\text{CH}}}_{3}{{\\text{CO}}}_{2}^{\\text{−}}]}",
    "EQ:58": "\\times"
  }
}