{
  "chapter": 4,
  "titleEn": "Stoichiometry of Chemical Reactions",
  "titleIs": "Magn- og efnareikningar",
  "sections": [
    {
      "id": "4.1",
      "titleEn": "Writing and Balancing Chemical Equations",
      "titleIs": "Ritun og jöfnun efnajafna"
    },
    {
      "id": "4.2",
      "titleEn": "Classifying Chemical Reactions",
      "titleIs": "Flokkun efnahvarfa"
    },
    {
      "id": "4.3",
      "titleEn": "Reaction Stoichiometry",
      "titleIs": "Magn- og efnareikningar í efnahvörfum"
    },
    {
      "id": "4.4",
      "titleEn": "Reaction Yields",
      "titleIs": "Afköst efnahvarfa"
    },
    {
      "id": "4.5",
      "titleEn": "Quantitative Chemical Analysis",
      "titleIs": "Magngreining í efnafræði"
    }
  ],
  "status": {
    "extraction": {
      "complete": true,
      "date": "2026-01-12"
    },
    "mtReady": {
      "complete": false
    },
    "mtOutput": {
      "complete": true,
      "date": "2026-01-12"
    },
    "linguisticReview": {
      "complete": false
    },
    "tmCreated": {
      "complete": true,
      "notes": "Currently being aligned in Matecat",
      "date": "2026-01-12"
    },
    "injection": {
      "complete": false
    },
    "rendering": {
      "complete": false
    },
    "publication": {
      "mtPreview": {
        "complete": true,
        "date": "2026-01-13",
        "notes": "MT with Chemistry Reader tags (11 files, 79 tags)"
      },
      "faithful": {
        "complete": false
      },
      "localized": {
        "complete": false
      }
    }
  },
  "images": {
    "total": null,
    "translated": 0,
    "status": "not-started"
  },
  "notes": "Matecat complete. Ready for Pass 1 or MT preview publication."
}
